helloworld.py
harrytsz01-0.0.1.dist-info/METADATA
harrytsz01-0.0.1.dist-info/WHEEL
harrytsz01-0.0.1.dist-info/top_level.txt
harrytsz01-0.0.1.dist-info/RECORD
