Metadata-Version: 2.1
Name: harrytsz01
Version: 0.0.1
Summary: Say hello
Home-page: UNKNOWN
Author: UNKNOWN
Author-email: UNKNOWN
License: UNKNOWN
Platform: UNKNOWN
